optivgi/__init__.py
optivgi/scm_runner.py
optivgi/threads.py
optivgi/translation.py
optivgi/utils.py
optivgi/scm/__init__.py
optivgi/scm/algorithm.py
optivgi/scm/constants.py
optivgi/scm/ev.py
optivgi/scm/go_algorithm.py
optivgi/scm/pulp_numerical_algorithm.py
optivgi-0.1.9.dist-info/licenses/LICENSE
optivgi-0.1.9.dist-info/METADATA
optivgi-0.1.9.dist-info/WHEEL
optivgi-0.1.9.dist-info/top_level.txt
optivgi-0.1.9.dist-info/RECORD
