Metadata-Version: 2.4
Name: optivgi
Version: 0.1.9
Summary: An EV smart charging management application designed to optimize electric vehicle charging based on power or pricing constraints.
Author-email: Nithin Manne <nmanne@anl.gov>, Jason Harper <jharper@anl.gov>
License:                                  Apache License
Project-URL: Homepage, https://github.com/argonne-vci/Opti-VGI
Project-URL: Documentation, https://argonne-vci.github.io/Opti-VGI
Project-URL: Issues, https://github.com/argonne-vci/Opti-VGI/issues
Classifier: Programming Language :: Python :: 3
Classifier: License :: OSI Approved :: Apache Software License
Classifier: Operating System :: OS Independent
Requires-Python: >=3.11
License-File: LICENSE
Requires-Dist: pulp
Provides-Extra: dev
Requires-Dist: pylint; extra == "dev"
Requires-Dist: build; extra == "dev"
Requires-Dist: setuptools; extra == "dev"
Requires-Dist: sphinx; extra == "dev"
Requires-Dist: furo; extra == "dev"
Requires-Dist: sphinx-autodoc-typehints; extra == "dev"
Dynamic: license-file
